okerrupdate/__init__.py
okerrupdate/utils.py
okerrupdate/version.py
okerrupdate/contrib/okerrmod
okerrupdate/mods-available/backups/_config
okerrupdate/mods-available/backups/_info
okerrupdate/mods-available/backups/check
okerrupdate/mods-available/client_ip/_config
okerrupdate/mods-available/client_ip/_info
okerrupdate/mods-available/client_ip/check
okerrupdate/mods-available/df/_config
okerrupdate/mods-available/df/_info
okerrupdate/mods-available/df/check
okerrupdate/mods-available/dirsize/_config
okerrupdate/mods-available/dirsize/_info
okerrupdate/mods-available/dirsize/check
okerrupdate/mods-available/empty/_config
okerrupdate/mods-available/empty/_info
okerrupdate/mods-available/empty/check
okerrupdate/mods-available/la/_config
okerrupdate/mods-available/la/_info
okerrupdate/mods-available/la/check
okerrupdate/mods-available/la3/_config
okerrupdate/mods-available/la3/_info
okerrupdate/mods-available/la3/check
okerrupdate/mods-available/linecount/_config
okerrupdate/mods-available/linecount/_info
okerrupdate/mods-available/linecount/check
okerrupdate/mods-available/maxfilesz/_config
okerrupdate/mods-available/maxfilesz/_info
okerrupdate/mods-available/maxfilesz/check
okerrupdate/mods-available/notempty/_config
okerrupdate/mods-available/notempty/_info
okerrupdate/mods-available/notempty/check
okerrupdate/mods-available/ok/check
okerrupdate/mods-available/opentcp/_config
okerrupdate/mods-available/opentcp/_info
okerrupdate/mods-available/opentcp/check
okerrupdate/mods-available/runline/_config
okerrupdate/mods-available/runline/_info
okerrupdate/mods-available/runline/check
okerrupdate/mods-available/runstatus/_config
okerrupdate/mods-available/runstatus/_info
okerrupdate/mods-available/runstatus/check
okerrupdate/mods-available/runtime/_config
okerrupdate/mods-available/runtime/_info
okerrupdate/mods-available/runtime/check
okerrupdate/mods-available/sql/_config
okerrupdate/mods-available/sql/_info
okerrupdate/mods-available/sql/check
okerrupdate-2.1.3.dist-info/METADATA
okerrupdate-2.1.3.dist-info/WHEEL
okerrupdate-2.1.3.dist-info/entry_points.txt
okerrupdate-2.1.3.dist-info/RECORD
