Metadata-Version: 2.4
Name: okerrupdate
Version: 2.1.3
Summary: okerr monitoring: client-side module and utilities
Project-URL: Homepage, https://github.com/yaroslaff/okerrupdate
Project-URL: Issues, https://github.com/yaroslaff/okerrupdate/issues
Author-email: Yaroslav Polyakov <yaroslaff@gmail.com>
Classifier: License :: OSI Approved :: MIT License
Classifier: Operating System :: OS Independent
Classifier: Programming Language :: Python :: 3
Requires-Python: >=3.8
Requires-Dist: psutil>=6.0.0
Requires-Dist: python-dotenv>=1.0.1
Requires-Dist: requests>=2.32.3
Requires-Dist: urllib3>=2.6.0
